{"ppo_epoch": 4, "seed": 1, "alpha": 0.99, "entropy_coef": 0.01, "no_cuda": false, "algo": "a2c", "window_length": 1, "vis_interval": 100, "num_steps": 5, "folder": "./results", "num_processes": 16, "use_gae": false, "max_grad_norm": 0.5, "log_dir": "./gym_results/", "cuda": true, "clip_param": 0.2, "tau": 0.95, "value_loss_coef": 0.5, "recurrent_policy": false, "eps": 1e-05, "gamma": 0.99, "num_frames": 10000000.0, "vis": true, "rmsize": 6000000, "num_stack": 4, "batch_size": 32, "log_interval": 10, "save_interval": 100, "lr": 0.0007, "no_vis": false, "env_name": "SeaquestNoFrameskip-v4", "save_dir": "./trained_models/"}